sphinx_localtime/__init__.py
sphinx_localtime/_static/dayjs/LICENSE
sphinx_localtime/_static/dayjs/advancedFormat.js
sphinx_localtime/_static/dayjs/dayjs.min.js
sphinx_localtime/_static/dayjs/timezone.js
sphinx_localtime/_static/dayjs/utc.js
sphinx_localtime-0.1.1.dist-info/licenses/LICENSE
sphinx_localtime-0.1.1.dist-info/WHEEL
sphinx_localtime-0.1.1.dist-info/METADATA
sphinx_localtime-0.1.1.dist-info/RECORD
