Metadata-Version: 2.4
Name: sphinx-localtime
Version: 0.1.1
Summary: Sphinx extension to convert times to browsers local times
Author: Richard Darst
Requires-Python: >=3.6
Classifier: License :: OSI Approved :: MIT License
License-File: LICENSE
Requires-Dist: Sphinx>=4
Requires-Dist: python-dateutil
Requires-Dist: pytz
Requires-Dist: pytest ; extra == "test"
Provides-Extra: test
